ieugwaspy/__init__.py
ieugwaspy/api.py
ieugwaspy/backwards.py
ieugwaspy/config.py
ieugwaspy/query.py
ieugwaspy/variants.py
tests/__init__.py
tests/conftest.py
tests/test_api.py
ieugwaspy-1.0.5.dist-info/LICENSE
ieugwaspy-1.0.5.dist-info/METADATA
ieugwaspy-1.0.5.dist-info/WHEEL
ieugwaspy-1.0.5.dist-info/top_level.txt
ieugwaspy-1.0.5.dist-info/RECORD
