Metadata-Version: 2.2
Name: ieugwaspy
Version: 1.0.5
Summary: Python interface to IEU GWAS database API
Home-page: https://mrcieu.github.io/ieugwaspy/
Author: Tom Gaunt
Author-email: tom@biocompute.org.uk
Classifier: Programming Language :: Python :: 3
Classifier: License :: OSI Approved :: MIT License
Classifier: Operating System :: OS Independent
Requires-Python: >=3.6
License-File: LICENSE
Requires-Dist: requests
Requires-Dist: retry
Dynamic: author
Dynamic: author-email
Dynamic: classifier
Dynamic: description
Dynamic: description-content-type
Dynamic: home-page
Dynamic: requires-dist
Dynamic: requires-python
Dynamic: summary
